[
    {
        "date":1533081600000,
        "amount":-2500.0,
        "description":"Shopping",
        "payee":"",
        "source_file":"data_lake\\staging\\01-2018-30-2018-banking-statment-dataset.json"
    },
    {
        "date":1533081600000,
        "amount":-324.0,
        "description":"Shopping",
        "payee":"",
        "source_file":"data_lake\\staging\\01-2018-30-2018-banking-statment-dataset.json"
    },
    {
        "date":1533168000000,
        "amount":0.0,
        "description":"",
        "payee":"",
        "source_file":"data_lake\\staging\\01-2018-30-2018-banking-statment-dataset.json"
    },
    {
        "date":1533254400000,
        "amount":-404.38,
        "description":"Shopping",
        "payee":"",
        "source_file":"data_lake\\staging\\01-2018-30-2018-banking-statment-dataset.json"
    },
    {
        "date":1533340800000,
        "amount":-10000.0,
        "description":"ATM",
        "payee":"",
        "source_file":"data_lake\\staging\\01-2018-30-2018-banking-statment-dataset.json"
    },
    {
        "date":1533340800000,
        "amount":-1395.0,
        "description":"Shopping",
        "payee":"",
        "source_file":"data_lake\\staging\\01-2018-30-2018-banking-statment-dataset.json"
    },
    {
        "date":1533340800000,
        "amount":-225.0,
        "description":"Shopping",
        "payee":"",
        "source_file":"data_lake\\staging\\01-2018-30-2018-banking-statment-dataset.json"
    },
    {
        "date":1533340800000,
        "amount":-110.0,
        "description":"Restaurant",
        "payee":"",
        "source_file":"data_lake\\staging\\01-2018-30-2018-banking-statment-dataset.json"
    },
    {
        "date":1533340800000,
        "amount":-100.0,
        "description":"Shopping",
        "payee":"",
        "source_file":"data_lake\\staging\\01-2018-30-2018-banking-statment-dataset.json"
    },
    {
        "date":1533427200000,
        "amount":0.0,
        "description":"",
        "payee":"",
        "source_file":"data_lake\\staging\\01-2018-30-2018-banking-statment-dataset.json"
    },
    {
        "date":1533513600000,
        "amount":-818.0,
        "description":"Shopping",
        "payee":"",
        "source_file":"data_lake\\staging\\01-2018-30-2018-banking-statment-dataset.json"
    },
    {
        "date":1533513600000,
        "amount":21.62,
        "description":"Interest",
        "payee":"",
        "source_file":"data_lake\\staging\\01-2018-30-2018-banking-statment-dataset.json"
    },
    {
        "date":1533600000000,
        "amount":-2704.84,
        "description":"Shopping",
        "payee":"",
        "source_file":"data_lake\\staging\\01-2018-30-2018-banking-statment-dataset.json"
    },
    {
        "date":1533686400000,
        "amount":0.0,
        "description":"",
        "payee":"",
        "source_file":"data_lake\\staging\\01-2018-30-2018-banking-statment-dataset.json"
    },
    {
        "date":1533772800000,
        "amount":-2053.0,
        "description":"Shopping",
        "payee":"",
        "source_file":"data_lake\\staging\\01-2018-30-2018-banking-statment-dataset.json"
    },
    {
        "date":1533859200000,
        "amount":-659.75,
        "description":"Medical",
        "payee":"",
        "source_file":"data_lake\\staging\\01-2018-30-2018-banking-statment-dataset.json"
    },
    {
        "date":1533859200000,
        "amount":-404.38,
        "description":"Entertainment",
        "payee":"",
        "source_file":"data_lake\\staging\\01-2018-30-2018-banking-statment-dataset.json"
    },
    {
        "date":1533945600000,
        "amount":-921.0,
        "description":"Shopping",
        "payee":"",
        "source_file":"data_lake\\staging\\01-2018-30-2018-banking-statment-dataset.json"
    },
    {
        "date":1533945600000,
        "amount":-853.0,
        "description":"Shopping",
        "payee":"",
        "source_file":"data_lake\\staging\\01-2018-30-2018-banking-statment-dataset.json"
    },
    {
        "date":1533945600000,
        "amount":-577.5,
        "description":"Travel",
        "payee":"",
        "source_file":"data_lake\\staging\\01-2018-30-2018-banking-statment-dataset.json"
    },
    {
        "date":1533945600000,
        "amount":-397.0,
        "description":"Shopping",
        "payee":"",
        "source_file":"data_lake\\staging\\01-2018-30-2018-banking-statment-dataset.json"
    },
    {
        "date":1533945600000,
        "amount":-130.0,
        "description":"Entertainment",
        "payee":"",
        "source_file":"data_lake\\staging\\01-2018-30-2018-banking-statment-dataset.json"
    },
    {
        "date":1533945600000,
        "amount":-108.0,
        "description":"Shopping",
        "payee":"",
        "source_file":"data_lake\\staging\\01-2018-30-2018-banking-statment-dataset.json"
    },
    {
        "date":1534032000000,
        "amount":-1375.0,
        "description":"Shopping",
        "payee":"",
        "source_file":"data_lake\\staging\\01-2018-30-2018-banking-statment-dataset.json"
    },
    {
        "date":1534032000000,
        "amount":-1024.0,
        "description":"Shopping",
        "payee":"",
        "source_file":"data_lake\\staging\\01-2018-30-2018-banking-statment-dataset.json"
    },
    {
        "date":1534118400000,
        "amount":-50.0,
        "description":"Shopping",
        "payee":"",
        "source_file":"data_lake\\staging\\01-2018-30-2018-banking-statment-dataset.json"
    },
    {
        "date":1534118400000,
        "amount":20.29,
        "description":"Interest",
        "payee":"",
        "source_file":"data_lake\\staging\\01-2018-30-2018-banking-statment-dataset.json"
    },
    {
        "date":1534204800000,
        "amount":-1305.0,
        "description":"Medical",
        "payee":"",
        "source_file":"data_lake\\staging\\01-2018-30-2018-banking-statment-dataset.json"
    },
    {
        "date":1534204800000,
        "amount":-931.0,
        "description":"Shopping",
        "payee":"",
        "source_file":"data_lake\\staging\\01-2018-30-2018-banking-statment-dataset.json"
    },
    {
        "date":1534291200000,
        "amount":-10000.0,
        "description":"ATM",
        "payee":"",
        "source_file":"data_lake\\staging\\01-2018-30-2018-banking-statment-dataset.json"
    },
    {
        "date":1534377600000,
        "amount":-14000.0,
        "description":"Rent",
        "payee":"",
        "source_file":"data_lake\\staging\\01-2018-30-2018-banking-statment-dataset.json"
    },
    {
        "date":1534464000000,
        "amount":-2800.52,
        "description":"Shopping",
        "payee":"",
        "source_file":"data_lake\\staging\\01-2018-30-2018-banking-statment-dataset.json"
    },
    {
        "date":1534550400000,
        "amount":-11610.0,
        "description":"Shopping",
        "payee":"",
        "source_file":"data_lake\\staging\\01-2018-30-2018-banking-statment-dataset.json"
    },
    {
        "date":1534550400000,
        "amount":-8400.0,
        "description":"Shopping",
        "payee":"",
        "source_file":"data_lake\\staging\\01-2018-30-2018-banking-statment-dataset.json"
    },
    {
        "date":1534550400000,
        "amount":-8296.0,
        "description":"Shopping",
        "payee":"",
        "source_file":"data_lake\\staging\\01-2018-30-2018-banking-statment-dataset.json"
    },
    {
        "date":1534550400000,
        "amount":-410.0,
        "description":"Shopping",
        "payee":"",
        "source_file":"data_lake\\staging\\01-2018-30-2018-banking-statment-dataset.json"
    },
    {
        "date":1534636800000,
        "amount":-412.0,
        "description":"Shopping",
        "payee":"",
        "source_file":"data_lake\\staging\\01-2018-30-2018-banking-statment-dataset.json"
    },
    {
        "date":1534723200000,
        "amount":21.0,
        "description":"Interest",
        "payee":"",
        "source_file":"data_lake\\staging\\01-2018-30-2018-banking-statment-dataset.json"
    },
    {
        "date":1534809600000,
        "amount":0.0,
        "description":"",
        "payee":"",
        "source_file":"data_lake\\staging\\01-2018-30-2018-banking-statment-dataset.json"
    },
    {
        "date":1534896000000,
        "amount":-10000.0,
        "description":"ATM",
        "payee":"",
        "source_file":"data_lake\\staging\\01-2018-30-2018-banking-statment-dataset.json"
    },
    {
        "date":1534982400000,
        "amount":-18777.0,
        "description":"Shopping",
        "payee":"",
        "source_file":"data_lake\\staging\\01-2018-30-2018-banking-statment-dataset.json"
    },
    {
        "date":1534982400000,
        "amount":-685.0,
        "description":"Medical",
        "payee":"",
        "source_file":"data_lake\\staging\\01-2018-30-2018-banking-statment-dataset.json"
    },
    {
        "date":1534982400000,
        "amount":-126.0,
        "description":"Restaurant",
        "payee":"",
        "source_file":"data_lake\\staging\\01-2018-30-2018-banking-statment-dataset.json"
    },
    {
        "date":1535068800000,
        "amount":0.0,
        "description":"",
        "payee":"",
        "source_file":"data_lake\\staging\\01-2018-30-2018-banking-statment-dataset.json"
    },
    {
        "date":1535155200000,
        "amount":-10000.0,
        "description":"ATM",
        "payee":"",
        "source_file":"data_lake\\staging\\01-2018-30-2018-banking-statment-dataset.json"
    },
    {
        "date":1535155200000,
        "amount":-772.0,
        "description":"Shopping",
        "payee":"",
        "source_file":"data_lake\\staging\\01-2018-30-2018-banking-statment-dataset.json"
    },
    {
        "date":1535155200000,
        "amount":-764.0,
        "description":"Shopping",
        "payee":"",
        "source_file":"data_lake\\staging\\01-2018-30-2018-banking-statment-dataset.json"
    },
    {
        "date":1535155200000,
        "amount":-548.0,
        "description":"Shopping",
        "payee":"",
        "source_file":"data_lake\\staging\\01-2018-30-2018-banking-statment-dataset.json"
    },
    {
        "date":1535155200000,
        "amount":-445.0,
        "description":"Shopping",
        "payee":"",
        "source_file":"data_lake\\staging\\01-2018-30-2018-banking-statment-dataset.json"
    },
    {
        "date":1535155200000,
        "amount":-399.0,
        "description":"Shopping",
        "payee":"",
        "source_file":"data_lake\\staging\\01-2018-30-2018-banking-statment-dataset.json"
    },
    {
        "date":1535155200000,
        "amount":-386.0,
        "description":"Shopping",
        "payee":"",
        "source_file":"data_lake\\staging\\01-2018-30-2018-banking-statment-dataset.json"
    },
    {
        "date":1535241600000,
        "amount":0.0,
        "description":"",
        "payee":"",
        "source_file":"data_lake\\staging\\01-2018-30-2018-banking-statment-dataset.json"
    },
    {
        "date":1535328000000,
        "amount":-2949.49,
        "description":"Shopping",
        "payee":"",
        "source_file":"data_lake\\staging\\01-2018-30-2018-banking-statment-dataset.json"
    },
    {
        "date":1535414400000,
        "amount":0.0,
        "description":"",
        "payee":"",
        "source_file":"data_lake\\staging\\01-2018-30-2018-banking-statment-dataset.json"
    },
    {
        "date":1535500800000,
        "amount":-1380.0,
        "description":"Shopping",
        "payee":"",
        "source_file":"data_lake\\staging\\01-2018-30-2018-banking-statment-dataset.json"
    },
    {
        "date":1535587200000,
        "amount":-3300.0,
        "description":"Shopping",
        "payee":"",
        "source_file":"data_lake\\staging\\01-2018-30-2018-banking-statment-dataset.json"
    },
    {
        "date":1535587200000,
        "amount":22.12,
        "description":"Interest",
        "payee":"",
        "source_file":"data_lake\\staging\\01-2018-30-2018-banking-statment-dataset.json"
    },
    {
        "date":1535673600000,
        "amount":-300000.0,
        "description":"Hotel",
        "payee":"Konko",
        "source_file":"data_lake\\staging\\DOCX_entry.json"
    },
    {
        "date":1535673600000,
        "amount":-200000.0,
        "description":"Travel",
        "payee":"Batik Air",
        "source_file":"data_lake\\staging\\DOCX_entry.json"
    },
    {
        "date":1535673600000,
        "amount":-892.5,
        "description":"Travel",
        "payee":"",
        "source_file":"data_lake\\staging\\01-2018-30-2018-banking-statment-dataset.json"
    },
    {
        "date":1535673600000,
        "amount":-590.0,
        "description":"Travel",
        "payee":"",
        "source_file":"data_lake\\staging\\01-2018-30-2018-banking-statment-dataset.json"
    },
    {
        "date":1535673600000,
        "amount":-340.0,
        "description":"Shopping",
        "payee":"",
        "source_file":"data_lake\\staging\\01-2018-30-2018-banking-statment-dataset.json"
    },
    {
        "date":1535673600000,
        "amount":250254.0,
        "description":"Salary",
        "payee":"",
        "source_file":"data_lake\\staging\\01-2018-30-2018-banking-statment-dataset.json"
    },
    {
        "date":1535760000000,
        "amount":-830.0,
        "description":"Restaurant",
        "payee":"",
        "source_file":"data_lake\\staging\\01-2018-30-2018-banking-statment-dataset.json"
    },
    {
        "date":1535760000000,
        "amount":-200.0,
        "description":"Shopping",
        "payee":"",
        "source_file":"data_lake\\staging\\01-2018-30-2018-banking-statment-dataset.json"
    },
    {
        "date":1535760000000,
        "amount":-33.5,
        "description":"Entertainment",
        "payee":"",
        "source_file":"data_lake\\staging\\01-2018-30-2018-banking-statment-dataset.json"
    },
    {
        "date":1535846400000,
        "amount":0.0,
        "description":"",
        "payee":"",
        "source_file":"data_lake\\staging\\01-2018-30-2018-banking-statment-dataset.json"
    },
    {
        "date":1535932800000,
        "amount":0.0,
        "description":"",
        "payee":"",
        "source_file":"data_lake\\staging\\01-2018-30-2018-banking-statment-dataset.json"
    },
    {
        "date":1536019200000,
        "amount":0.0,
        "description":"",
        "payee":"",
        "source_file":"data_lake\\staging\\01-2018-30-2018-banking-statment-dataset.json"
    },
    {
        "date":1536105600000,
        "amount":0.0,
        "description":"",
        "payee":"",
        "source_file":"data_lake\\staging\\01-2018-30-2018-banking-statment-dataset.json"
    },
    {
        "date":1536192000000,
        "amount":-2880.09,
        "description":"Shopping",
        "payee":"",
        "source_file":"data_lake\\staging\\01-2018-30-2018-banking-statment-dataset.json"
    },
    {
        "date":1536278400000,
        "amount":0.0,
        "description":"",
        "payee":"",
        "source_file":"data_lake\\staging\\01-2018-30-2018-banking-statment-dataset.json"
    },
    {
        "date":1536364800000,
        "amount":-10000.0,
        "description":"ATM",
        "payee":"",
        "source_file":"data_lake\\staging\\01-2018-30-2018-banking-statment-dataset.json"
    },
    {
        "date":1536364800000,
        "amount":-3257.0,
        "description":"Shopping",
        "payee":"",
        "source_file":"data_lake\\staging\\01-2018-30-2018-banking-statment-dataset.json"
    },
    {
        "date":1536451200000,
        "amount":0.0,
        "description":"",
        "payee":"",
        "source_file":"data_lake\\staging\\01-2018-30-2018-banking-statment-dataset.json"
    },
    {
        "date":1536537600000,
        "amount":-20000.0,
        "description":"Rent",
        "payee":"",
        "source_file":"data_lake\\staging\\01-2018-30-2018-banking-statment-dataset.json"
    },
    {
        "date":1536624000000,
        "amount":-202.19,
        "description":"Entertainment",
        "payee":"",
        "source_file":"data_lake\\staging\\01-2018-30-2018-banking-statment-dataset.json"
    },
    {
        "date":1536710400000,
        "amount":0.0,
        "description":"",
        "payee":"",
        "source_file":"data_lake\\staging\\01-2018-30-2018-banking-statment-dataset.json"
    },
    {
        "date":1536796800000,
        "amount":0.0,
        "description":"",
        "payee":"",
        "source_file":"data_lake\\staging\\01-2018-30-2018-banking-statment-dataset.json"
    },
    {
        "date":1536883200000,
        "amount":0.0,
        "description":"",
        "payee":"",
        "source_file":"data_lake\\staging\\01-2018-30-2018-banking-statment-dataset.json"
    },
    {
        "date":1536969600000,
        "amount":-5089.0,
        "description":"Shopping",
        "payee":"",
        "source_file":"data_lake\\staging\\01-2018-30-2018-banking-statment-dataset.json"
    },
    {
        "date":1536969600000,
        "amount":-243.66,
        "description":"Entertainment",
        "payee":"",
        "source_file":"data_lake\\staging\\01-2018-30-2018-banking-statment-dataset.json"
    },
    {
        "date":1537056000000,
        "amount":-2569.88,
        "description":"Shopping",
        "payee":"",
        "source_file":"data_lake\\staging\\01-2018-30-2018-banking-statment-dataset.json"
    },
    {
        "date":1537142400000,
        "amount":0.0,
        "description":"",
        "payee":"",
        "source_file":"data_lake\\staging\\01-2018-30-2018-banking-statment-dataset.json"
    },
    {
        "date":1537228800000,
        "amount":19.27,
        "description":"Interest",
        "payee":"",
        "source_file":"data_lake\\staging\\01-2018-30-2018-banking-statment-dataset.json"
    },
    {
        "date":1537315200000,
        "amount":-10000.0,
        "description":"ATM",
        "payee":"",
        "source_file":"data_lake\\staging\\01-2018-30-2018-banking-statment-dataset.json"
    },
    {
        "date":1537401600000,
        "amount":-202.19,
        "description":"Entertainment",
        "payee":"",
        "source_file":"data_lake\\staging\\01-2018-30-2018-banking-statment-dataset.json"
    },
    {
        "date":1537488000000,
        "amount":0.0,
        "description":"",
        "payee":"",
        "source_file":"data_lake\\staging\\01-2018-30-2018-banking-statment-dataset.json"
    },
    {
        "date":1537574400000,
        "amount":0.0,
        "description":"",
        "payee":"",
        "source_file":"data_lake\\staging\\01-2018-30-2018-banking-statment-dataset.json"
    },
    {
        "date":1537660800000,
        "amount":-1000.0,
        "description":"Medical",
        "payee":"",
        "source_file":"data_lake\\staging\\01-2018-30-2018-banking-statment-dataset.json"
    },
    {
        "date":1537747200000,
        "amount":0.0,
        "description":"",
        "payee":"",
        "source_file":"data_lake\\staging\\01-2018-30-2018-banking-statment-dataset.json"
    },
    {
        "date":1537833600000,
        "amount":0.0,
        "description":"",
        "payee":"",
        "source_file":"data_lake\\staging\\01-2018-30-2018-banking-statment-dataset.json"
    },
    {
        "date":1537920000000,
        "amount":-3000.65,
        "description":"Shopping",
        "payee":"",
        "source_file":"data_lake\\staging\\01-2018-30-2018-banking-statment-dataset.json"
    },
    {
        "date":1537920000000,
        "amount":2250.0,
        "description":"Interest",
        "payee":"",
        "source_file":"data_lake\\staging\\01-2018-30-2018-banking-statment-dataset.json"
    },
    {
        "date":1538006400000,
        "amount":-202.19,
        "description":"Entertainment",
        "payee":"",
        "source_file":"data_lake\\staging\\01-2018-30-2018-banking-statment-dataset.json"
    },
    {
        "date":1538092800000,
        "amount":-1869.0,
        "description":"Shopping",
        "payee":"",
        "source_file":"data_lake\\staging\\01-2018-30-2018-banking-statment-dataset.json"
    },
    {
        "date":1538092800000,
        "amount":22.5,
        "description":"Interest",
        "payee":"",
        "source_file":"data_lake\\staging\\01-2018-30-2018-banking-statment-dataset.json"
    },
    {
        "date":1538092800000,
        "amount":250254.0,
        "description":"Salary",
        "payee":"",
        "source_file":"data_lake\\staging\\01-2018-30-2018-banking-statment-dataset.json"
    },
    {
        "date":1538179200000,
        "amount":-2108.0,
        "description":"Shopping - Shopping - Buying Supplies - Shopping - - Tape - Book - Pen - Shopping - - Tape - Book - Pen - Shopping - Shopping - Buying Supplies - Shopping - Shopping - Buying Supplies - Shopping - Shopping - Shopping - Buying Supplies - Shopping - Buying Supplies - Shopping - Buying Supplies - Shopping - Shopping - Buying Supplies - Shopping - Shopping - Buying Supplies - Shopping - Shopping - - Tape - Book - Pen - Shopping - - Tape - Book - Pen - Shopping - - Tape - Book - Pen - Shopping - Buying Supplies - Shopping - Shopping - - Tape - Book - Pen - Shopping - Buying Supplies - Shopping - - Tape - Book - Pen - Shopping - Buying Supplies",
        "payee":"Store1",
        "source_file":"data_lake\\staging\\Second_Entry.json, data_lake\\staging\\30092018_First_entry.json, data_lake\\staging\\Second_Entry.json, data_lake\\staging\\01-2018-30-2018-banking-statment-dataset.json, data_lake\\staging\\30092018_First_entry.json, data_lake\\staging\\01-2018-30-2018-banking-statment-dataset.json, data_lake\\staging\\30092018_First_entry.json, data_lake\\staging\\Second_Entry.json, data_lake\\staging\\01-2018-30-2018-banking-statment-dataset.json, data_lake\\staging\\01-2018-30-2018-banking-statment-dataset.json, data_lake\\staging\\30092018_First_entry.json, data_lake\\staging\\Second_Entry.json, data_lake\\staging\\30092018_First_entry.json, data_lake\\staging\\30092018_First_entry.json, data_lake\\staging\\01-2018-30-2018-banking-statment-dataset.json, data_lake\\staging\\01-2018-30-2018-banking-statment-dataset.json, data_lake\\staging\\30092018_First_entry.json, data_lake\\staging\\30092018_First_entry.json, data_lake\\staging\\01-2018-30-2018-banking-statment-dataset.json, data_lake\\staging\\30092018_First_entry.json, data_lake\\staging\\01-2018-30-2018-banking-statment-dataset.json, data_lake\\staging\\01-2018-30-2018-banking-statment-dataset.json, data_lake\\staging\\Second_Entry.json, data_lake\\staging\\Second_Entry.json, data_lake\\staging\\30092018_First_entry.json, data_lake\\staging\\Second_Entry.json, data_lake\\staging\\30092018_First_entry.json"
    },
    {
        "date":1538179200000,
        "amount":-1180.0,
        "description":"Shopping",
        "payee":"",
        "source_file":"data_lake\\staging\\01-2018-30-2018-banking-statment-dataset.json"
    },
    {
        "date":1538179200000,
        "amount":-202.19,
        "description":"Shopping",
        "payee":"",
        "source_file":"data_lake\\staging\\01-2018-30-2018-banking-statment-dataset.json"
    },
    {
        "date":1538265600000,
        "amount":-10000.0,
        "description":"ATM - Cash out - ATM - ATM - Cash out - ATM - ATM - Cash out - ATM - ATM - ATM - Cash out - ATM - ATM - Cash out - ATM - ATM - Cash out - ATM - ATM - Cash out - ATM - ATM - Cash out - ATM - ATM - Cash out - ATM - ATM - ATM - Cash out - ATM - Cash out",
        "payee":"Bank - Bank - Mandiri - Mandiri - Bank - Mandiri - Bank - Mandiri - Bank - Mandiri - Bank - Bank - Mandiri - Mandiri",
        "source_file":"data_lake\\staging\\Second_Entry.json, data_lake\\staging\\30092018_First_entry.json, data_lake\\staging\\Second_Entry.json, data_lake\\staging\\01-2018-30-2018-banking-statment-dataset.json, data_lake\\staging\\30092018_First_entry.json, data_lake\\staging\\01-2018-30-2018-banking-statment-dataset.json, data_lake\\staging\\30092018_First_entry.json, data_lake\\staging\\Second_Entry.json, data_lake\\staging\\01-2018-30-2018-banking-statment-dataset.json, data_lake\\staging\\01-2018-30-2018-banking-statment-dataset.json, data_lake\\staging\\30092018_First_entry.json, data_lake\\staging\\Second_Entry.json, data_lake\\staging\\30092018_First_entry.json, data_lake\\staging\\30092018_First_entry.json, data_lake\\staging\\01-2018-30-2018-banking-statment-dataset.json, data_lake\\staging\\01-2018-30-2018-banking-statment-dataset.json, data_lake\\staging\\30092018_First_entry.json, data_lake\\staging\\30092018_First_entry.json, data_lake\\staging\\01-2018-30-2018-banking-statment-dataset.json, data_lake\\staging\\30092018_First_entry.json, data_lake\\staging\\01-2018-30-2018-banking-statment-dataset.json, data_lake\\staging\\01-2018-30-2018-banking-statment-dataset.json, data_lake\\staging\\Second_Entry.json, data_lake\\staging\\Second_Entry.json, data_lake\\staging\\30092018_First_entry.json, data_lake\\staging\\Second_Entry.json, data_lake\\staging\\30092018_First_entry.json"
    },
    {
        "date":1538265600000,
        "amount":-1185.0,
        "description":"Shopping",
        "payee":"",
        "source_file":"data_lake\\staging\\01-2018-30-2018-banking-statment-dataset.json"
    },
    {
        "date":1538265600000,
        "amount":-1155.75,
        "description":"Medical",
        "payee":"",
        "source_file":"data_lake\\staging\\01-2018-30-2018-banking-statment-dataset.json"
    },
    {
        "date":1538265600000,
        "amount":1673.0,
        "description":"Interest",
        "payee":"",
        "source_file":"data_lake\\staging\\01-2018-30-2018-banking-statment-dataset.json"
    }
]